{
	"backtraceGraph" : 
	{
		"commands" : 
		[
			"install"
		],
		"files" : 
		[
			"CMakeLists.txt"
		],
		"nodes" : 
		[
			{
				"file" : 0
			},
			{
				"command" : 0,
				"file" : 0,
				"line" : 97,
				"parent" : 0
			},
			{
				"command" : 0,
				"file" : 0,
				"line" : 104,
				"parent" : 0
			},
			{
				"command" : 0,
				"file" : 0,
				"line" : 110,
				"parent" : 0
			}
		]
	},
	"installers" : 
	[
		{
			"backtrace" : 1,
			"component" : "devel",
			"destination" : "lib/cmake/workflow",
			"paths" : 
			[
				{
					"from" : "vscode-cmake-build/config.toinstall.cmake",
					"to" : "workflow-config.cmake"
				}
			],
			"type" : "file"
		},
		{
			"backtrace" : 2,
			"component" : "devel",
			"destination" : "include/workflow",
			"paths" : 
			[
				"src/algorithm/DnsRoutine.h",
				"src/algorithm/MapReduce.h",
				"src/algorithm/MapReduce.inl",
				"src/protocol/ProtocolMessage.h",
				"src/protocol/http_parser.h",
				"src/protocol/HttpMessage.h",
				"src/protocol/HttpUtil.h",
				"src/protocol/redis_parser.h",
				"src/protocol/RedisMessage.h",
				"src/protocol/mysql_stream.h",
				"src/protocol/MySQLMessage.h",
				"src/protocol/MySQLMessage.inl",
				"src/protocol/MySQLResult.h",
				"src/protocol/MySQLResult.inl",
				"src/protocol/mysql_parser.h",
				"src/protocol/mysql_types.h",
				"src/protocol/mysql_byteorder.h",
				"src/protocol/SSLWrapper.h",
				"src/protocol/dns_parser.h",
				"src/protocol/DnsMessage.h",
				"src/protocol/DnsUtil.h",
				"src/server/WFServer.h",
				"src/server/WFDnsServer.h",
				"src/server/WFHttpServer.h",
				"src/server/WFRedisServer.h",
				"src/server/WFMySQLServer.h",
				"src/client/WFMySQLConnection.h",
				"src/client/WFDnsClient.h",
				"src/manager/DnsCache.h",
				"src/manager/WFGlobal.h",
				"src/manager/UpstreamManager.h",
				"src/manager/RouteManager.h",
				"src/manager/EndpointParams.h",
				"src/manager/WFFuture.h",
				"src/manager/WFFacilities.h",
				"src/manager/WFFacilities.inl",
				"src/util/EncodeStream.h",
				"src/util/LRUCache.h",
				"src/util/StringUtil.h",
				"src/util/URIParser.h",
				"src/util/MD5Util.h",
				"src/factory/WFConnection.h",
				"src/factory/WFTask.h",
				"src/factory/WFTask.inl",
				"src/factory/WFGraphTask.h",
				"src/factory/WFTaskError.h",
				"src/factory/WFTaskFactory.h",
				"src/factory/WFTaskFactory.inl",
				"src/factory/WFAlgoTaskFactory.h",
				"src/factory/WFAlgoTaskFactory.inl",
				"src/factory/Workflow.h",
				"src/factory/WFOperator.h",
				"src/factory/WFResourcePool.h",
				"src/nameservice/WFNameService.h",
				"src/nameservice/WFDnsResolver.h",
				"src/nameservice/WFServiceGovernance.h",
				"src/nameservice/UpstreamPolicies.h",
				"src/kernel/CommRequest.h",
				"src/kernel/CommScheduler.h",
				"src/kernel/Communicator.h",
				"src/kernel/SleepRequest.h",
				"src/kernel/ExecRequest.h",
				"src/kernel/IORequest.h",
				"src/kernel/Executor.h",
				"src/kernel/list.h",
				"src/kernel/mpoller.h",
				"src/kernel/poller.h",
				"src/kernel/msgqueue.h",
				"src/kernel/rbtree.h",
				"src/kernel/SubTask.h",
				"src/kernel/thrdpool.h",
				"src/kernel/IOService_thread.h"
			],
			"type" : "file"
		},
		{
			"backtrace" : 3,
			"component" : "devel",
			"destination" : "share/doc/workflow-0.9.9",
			"paths" : 
			[
				"README.md"
			],
			"type" : "file"
		}
	],
	"paths" : 
	{
		"build" : ".",
		"source" : "."
	}
}
